{"$schema":"https://json-schema.org/draft/2020-12/schema","$id":"https://example.org/cpcf/schemas/v0.4.0/trial-result-certificate.schema.json","title":"CPCF Trial Result Certificate Payload v0.4","type":"object","properties":{"schema_version":{"const":"0.4.0"},"result_id":{"type":"string","minLength":1,"maxLength":256},"protocol_id":{"type":"string","minLength":1,"maxLength":256},"protocol_digest":{"type":"string","pattern":"^sha256:[0-9a-f]{64}$"},"dataset_digest":{"type":"string","pattern":"^sha256:[0-9a-f]{64}$"},"analysis_executable_digest":{"type":"string","pattern":"^sha256:[0-9a-f]{64}$"},"observation_started_at":{"type":"string","format":"date-time"},"observation_ended_at":{"type":"string","format":"date-time"},"completed_at":{"type":"string","format":"date-time"},"effect_intervals":{"type":"object","minProperties":1,"additionalProperties":{"type":"object","properties":{"lower":{"type":"string"},"upper":{"type":"string"},"unit":{"type":"string","minLength":1,"maxLength":128}},"required":["lower","upper","unit"],"unevaluatedProperties":false}},"quality_intervals":{"type":"object"},"safety_intervals":{"type":"object"},"amendment_chain_digest":{"oneOf":[{"type":"string","pattern":"^sha256:[0-9a-f]{64}$"},{"type":"null"}]}},"required":["schema_version","result_id","protocol_id","protocol_digest","dataset_digest","analysis_executable_digest","observation_started_at","observation_ended_at","completed_at","effect_intervals","quality_intervals","safety_intervals","amendment_chain_digest"],"unevaluatedProperties":false}
